[{"verified": false, "w": 1, "h": 1, "icon": "https://web.poecdn.com/gen/image/WzI1LDE0LHsiZiI6IjJESXRlbXMvUmluZ3MvVGhlVGFtaW5nIiwidyI6MSwiaCI6MSwic2NhbGUiOjF9XQ/17c5d3d74b/TheTaming.png", "league": "Mirage", "id": "8ee28eec34983d19ff4585bfa2419c6790fa3870532a4d4cd450aa5827b32ec3", "name": "The Taming", "typeLine": "Prismatic Ring", "baseType": "Prismatic Ring", "rarity": "Unique", "ilvl": 80, "identified": true, "properties": [{"name": "Quality (Elemental Damage Modifiers)", "values": [["+20%", 1]], "displayMode": 0, "type": 6}], "requirements": [{"name": "Level", "values": [["30", 0]], "displayMode": 0, "type": 62}], "implicitMods": ["+10% to all Elemental Resistances"], "explicitMods": ["+29% to all Elemental Resistances", "10% chance to Freeze, Shock and Ignite", "48% increased Elemental Damage with Hits and Ailments for\neach type of Elemental Ailment on Enemy"], "flavourText": ["\"Moon after moon did Berek make fools\r", "Of the great and Untamed Three\r", "Until malice for a Brother\r", "Slew the hatred of the Other\r", "And Berek did hunt\r", "Alone and free.\"\r", "- Berek and the Untamed"], "frameType": 3, "x": 0, "y": 0, "inventoryId": "Ring"}, {"verified": false, "w": 1, "h": 1, "icon": "https://web.poecdn.com/gen/image/WzI1LDE0LHsiZiI6IjJESXRlbXMvQW11bGV0cy9TeW50aGVzaXNBY2N1cmFjeUFtdWxldCIsInciOjEsImgiOjEsInNjYWxlIjoxfV0/6062fd361e/SynthesisAccuracyAmulet.png", "league": "Mirage", "id": "d0b13dbd9ee64a1d108e544b936b62d5e7a01d7116a29897d53953dac07ecf68", "name": "Hyrri's Truth", "typeLine": "Jade Amulet", "baseType": "Jade Amulet", "rarity": "Unique", "ilvl": 73, "identified": true, "requirements": [{"name": "Level", "values": [["64", 0]], "displayMode": 0, "type": 62}], "enchantMods": ["Allocates Sovereignty"], "implicitMods": ["+24 to Dexterity"], "explicitMods": ["Grants Level 30 Precision Skill", "+40 to Dexterity", "+45% to Global Critical Strike Multiplier", "Bow Attacks have Culling Strike", "Precision has 100% increased Mana Reservation Efficiency"], "flavourText": ["Strike true, strike hard, and leave no survivors to retaliate."], "frameType": 3, "x": 0, "y": 0, "inventoryId": "Amulet"}, {"verified": false, "w": 1, "h": 2, "icon": "https://web.poecdn.com/gen/image/WzksMTQseyJmIjoiMkRJdGVtcy9GbGFza3Mvc3ByaW50IiwidyI6MSwiaCI6Miwic2NhbGUiOjEsImxldmVsIjoxLCJmaSI6dHJ1ZX1d/3f8edd74f2/sprint.png", "league": "Mirage", "id": "3190a24c172651d5394994dfa71fc3dac50ee68280ce73089a52bcf1e37f9097", "name": "", "typeLine": "Examiner's Quicksilver Flask of the Antelope", "baseType": "Quicksilver Flask", "rarity": "Magic", "ilvl": 86, "identified": true, "properties": [{"name": "Quality", "values": [["+2%", 1]], "displayMode": 0, "type": 6}, {"name": "Lasts {0} Seconds", "values": [["8", 1]], "displayMode": 3}, {"name": "Consumes {0} of {1} Charges on use", "values": [["30", 0], ["60", 0]], "displayMode": 3}, {"name": "Currently has {0} Charges", "values": [["60", 0]], "displayMode": 3}], "requirements": [{"name": "Level", "values": [["41", 0]], "displayMode": 0, "type": 62}], "utilityMods": ["40% increased Movement Speed"], "enchantMods": ["Used when Charges reach full"], "explicitMods": ["30% increased Duration", "47% increased Evasion Rating during Effect"], "descrText": "Right click to drink. Can only hold charges while in belt. Refills as you kill monsters.", "frameType": 1, "x": 2, "y": 0, "inventoryId": "Flask"}, {"verified": false, "w": 1, "h": 1, "icon": "https://web.poecdn.com/gen/image/WzI1LDE0LHsiZiI6IjJESXRlbXMvUmluZ3MvVGhlVGFtaW5nIiwidyI6MSwiaCI6MSwic2NhbGUiOjF9XQ/17c5d3d74b/TheTaming.png", "league": "Mirage", "id": "839e04d7ea4a218120fa4399046d1a8b2da04bc548ba7416462b1e033ffcec22", "name": "The Taming", "typeLine": "Prismatic Ring", "baseType": "Prismatic Ring", "rarity": "Unique", "ilvl": 80, "identified": true, "properties": [{"name": "Quality (Elemental Damage Modifiers)", "values": [["+20%", 1]], "displayMode": 0, "type": 6}], "requirements": [{"name": "Level", "values": [["30", 0]], "displayMode": 0, "type": 62}], "implicitMods": ["+10% to all Elemental Resistances"], "explicitMods": ["+29% to all Elemental Resistances", "10% chance to Freeze, Shock and Ignite", "48% increased Elemental Damage with Hits and Ailments for\neach type of Elemental Ailment on Enemy"], "flavourText": ["\"Moon after moon did Berek make fools\r", "Of the great and Untamed Three\r", "Until malice for a Brother\r", "Slew the hatred of the Other\r", "And Berek did hunt\r", "Alone and free.\"\r", "- Berek and the Untamed"], "frameType": 3, "x": 0, "y": 0, "inventoryId": "Ring2"}, {"verified": false, "w": 2, "h": 3, "icon": "https://web.poecdn.com/gen/image/WzI1LDE0LHsiZiI6IjJESXRlbXMvV2VhcG9ucy9PbmVIYW5kV2VhcG9ucy9PbmVIYW5kU3dvcmRzL0hhcmJpbmdlclN3b3JkVXBncmFkZWQiLCJ3IjoyLCJoIjozLCJzY2FsZSI6MX1d/bf1d1647f5/HarbingerSwordUpgraded.png", "league": "Mirage", "id": "0140349d88da143744621cde32bc21d99cd493dd00c27cfbdec6fd1bcda9074d", "sockets": [{"group": 0, "attr": "S", "sColour": "R"}, {"group": 0, "attr": "D", "sColour": "G"}, {"group": 0, "attr": "D", "sColour": "G"}], "name": "The Surging Thoughts", "typeLine": "Legion Sword", "baseType": "Legion Sword", "rarity": "Unique", "ilvl": 100, "identified": true, "properties": [{"name": "One Handed Sword", "values": [], "displayMode": 0}, {"name": "Quality", "values": [["+20%", 1]], "displayMode": 0, "type": 6}, {"name": "Physical Damage", "values": [["165-305", 1]], "displayMode": 0, "type": 9}, {"name": "Elemental Damage", "values": [["1-66", 6]], "displayMode": 0, "type": 10}, {"name": "Critical Strike Chance", "values": [["5.00%", 0]], "displayMode": 0, "type": 12}, {"name": "Attacks per Second", "values": [["1.20", 0]], "displayMode": 0, "type": 13}, {"name": "Weapon Range: {0} metres", "values": [["1.1", 0]], "displayMode": 3, "type": 14}], "requirements": [{"name": "Level", "values": [["62", 0]], "displayMode": 0, "type": 62}, {"name": "Str", "values": [["122", 0]], "displayMode": 1, "type": 63}, {"name": "Dex", "values": [["104", 0]], "displayMode": 1, "type": 64}], "implicitMods": ["40% increased Global Accuracy Rating"], "explicitMods": ["Grants Summon Greater Harbinger of the Arcane Skill", "Trigger Level 20 Storm Cascade when you Attack", "79% increased Spell Damage", "159% increased Physical Damage", "Adds 1 to 66 Lightning Damage", "Adds 1 to 65 Lightning Damage to Spells", "10% increased Area of Effect"], "flavourText": ["<<HBGAf>><<HBG02>><<HBGAm>><<HBG03>><<HBGAa>>\r", "<<HBGAk>><<HBG03>><<HBGC011>><<HBGAl>><<HBG03>><<HBGAo>><<HBGAe>>\r", "<<HBGC011>><<HBGAa>><<HBG00>><<HBGC07>>"], "frameType": 3, "x": 0, "y": 0, "inventoryId": "Weapon2", "socketedItems": []}, {"verified": false, "w": 2, "h": 2, "icon": "https://web.poecdn.com/gen/image/WzI1LDE0LHsiZiI6IjJESXRlbXMvQXJtb3Vycy9IZWxtZXRzL0V4dHJlbWVGb2N1cyIsInciOjIsImgiOjIsInNjYWxlIjoxfV0/d900d9764f/ExtremeFocus.png", "league": "Mirage", "id": "fda52d08fba8a69a462943ae04b7d0f3ccb93461aa7d863b7781bea924fd07a0", "sockets": [{"group": 0, "attr": "I", "sColour": "B"}, {"group": 1, "attr": "I", "sColour": "B"}, {"group": 1, "attr": "S", "sColour": "R"}, {"group": 2, "attr": "D", "sColour": "G"}], "name": "The Fledgling", "typeLine": "Lacquered Helmet", "baseType": "Lacquered Helmet", "rarity": "Unique", "ilvl": 83, "identified": true, "properties": [{"name": "Quality", "values": [["+20%", 1]], "displayMode": 0, "type": 6}, {"name": "Armour", "values": [["430", 1]], "displayMode": 0, "type": 16}, {"name": "Evasion Rating", "values": [["430", 1]], "displayMode": 0, "type": 17}], "requirements": [{"name": "Level", "values": [["51", 0]], "displayMode": 0, "type": 62}, {"name": "Str", "values": [["57", 0]], "displayMode": 1, "type": 63}, {"name": "Dex", "values": [["57", 0]], "displayMode": 1, "type": 64}], "explicitMods": ["158% increased Armour and Evasion", "40% increased Projectile Speed", "49% increased Projectile Damage", "Projectiles cannot collide with Enemies in Close Range", "Far Shot"], "flavourText": ["The single well-placed arrow that changes the world\r", "must be preceded by ten thousand practice shots."], "frameType": 3, "x": 0, "y": 0, "inventoryId": "Helm", "socketedItems": []}, {"verified": false, "w": 2, "h": 3, "icon": "https://web.poecdn.com/gen/image/WzI1LDE0LHsiZiI6IjJESXRlbXMvQXJtb3Vycy9Cb2R5QXJtb3Vycy9Cb2R5RGV4M0NVbmlxdWUiLCJ3IjoyLCJoIjozLCJzY2FsZSI6MX1d/fb532d6c21/BodyDex3CUnique.png", "league": "Mirage", "id": "6687081026a0acb637375b19b0b68c0ad38b80513b558a8c1249cb3cea6b8219", "sockets": [{"group": 0, "attr": "I", "sColour": "B"}, {"group": 0, "attr": "D", "sColour": "G"}, {"group": 0, "attr": "S", "sColour": "R"}, {"group": 0, "attr": "S", "sColour": "R"}, {"group": 0, "attr": "D", "sColour": "G"}, {"group": 0, "attr": "D", "sColour": "G"}], "name": "Hyrri's Ire", "typeLine": "Zodiac Leather", "baseType": "Zodiac Leather", "rarity": "Unique", "ilvl": 84, "identified": true, "properties": [{"name": "Quality", "values": [["+20%", 1]], "displayMode": 0, "type": 6}, {"name": "Evasion Rating", "values": [["2746", 1]], "displayMode": 0, "type": 17}], "requirements": [{"name": "Level", "values": [["65", 0]], "displayMode": 0, "type": 62}, {"name": "Dex", "values": [["197", 0]], "displayMode": 1, "type": 64}], "explicitMods": ["+30% chance to Suppress Spell Damage", "+44 to Dexterity", "168% increased Evasion Rating", "25% increased Chill Duration on Enemies", "115 to 176 Added Cold Damage with Bow Attacks"], "flavourText": ["Hyrri loosed a barrage of arrows,\r", "tipped with a poisoned hatred\r", "only oppression can ferment."], "frameType": 3, "x": 0, "y": 0, "inventoryId": "BodyArmour", "socketedItems": []}, {"verified": false, "w": 2, "h": 3, "icon": "https://web.poecdn.com/gen/image/WzI1LDE0LHsiZiI6IjJESXRlbXMvQXJtb3Vycy9TaGllbGRzL0hhcmJpbmdlclNoaWVsZFVwZ3JhZGVkIiwidyI6MiwiaCI6Mywic2NhbGUiOjF9XQ/a259d55fe1/HarbingerShieldUpgraded.png", "league": "Mirage", "id": "f7d3f80e7073c2d77b59559863995a2e61daf4866dd053232e9bbee3dfdb91be", "sockets": [{"group": 0, "attr": "I", "sColour": "B"}, {"group": 0, "attr": "I", "sColour": "B"}, {"group": 0, "attr": "S", "sColour": "R"}], "name": "The Immortal Will", "typeLine": "Archon Kite Shield", "baseType": "Archon Kite Shield", "rarity": "Unique", "ilvl": 83, "identified": true, "properties": [{"name": "Quality", "values": [["+20%", 1]], "displayMode": 0, "type": 6}, {"name": "Chance to Block", "values": [["27%", 1]], "displayMode": 0, "type": 15}, {"name": "Armour", "values": [["209", 1]], "displayMode": 0, "type": 16}, {"name": "Energy Shield", "values": [["43", 1]], "displayMode": 0, "type": 18}], "requirements": [{"name": "Level", "values": [["68", 0]], "displayMode": 0, "type": 62}, {"name": "Str", "values": [["85", 0]], "displayMode": 1, "type": 63}, {"name": "Int", "values": [["85", 0]], "displayMode": 1, "type": 65}], "implicitMods": ["+12% to all Elemental Resistances"], "explicitMods": ["Grants Summon Greater Harbinger of Focus Skill", "+77 to maximum Life", "+13% to all Elemental Resistances", "42 Mana gained when you Block", "+5% Chance to Block", "Channelling Skills deal 53% increased Damage"], "flavourText": ["<<HBGAa>><<HBG00>><<HBGAt>>\r", "<<HBGAa>><<HBG04>><<HBGAp>>\r", "<<HBGAa>><<HBG01>><<HBGAn>><<HBG04>><<HBGC01>>\r", "<<HBGAf>><<HBG02>><<HBGC05>>"], "frameType": 3, "x": 0, "y": 0, "inventoryId": "Offhand2", "socketedItems": []}]