[{"verified": false, "w": 2, "h": 3, "icon": "https://web.poecdn.com/gen/image/WzI1LDE0LHsiZiI6IjJESXRlbXMvV2VhcG9ucy9Ud29IYW5kV2VhcG9ucy9Cb3dzL0JvdzIiLCJ3IjoyLCJoIjozLCJzY2FsZSI6MX1d/0fcc51afcd/Bow2.png", "league": "Mirage", "id": "cfeaccbecaed7b53b66685f14dbc16861edfee3426a9358a7da10372bf192461", "sockets": [{"group": 0, "attr": "D", "sColour": "G"}, {"group": 1, "attr": "D", "sColour": "G"}, {"group": 2, "attr": "D", "sColour": "G"}, {"group": 2, "attr": "D", "sColour": "G"}, {"group": 3, "attr": "D", "sColour": "G"}], "name": "Torment Volley", "typeLine": "Grove Bow", "baseType": "Grove Bow", "rarity": "Rare", "ilvl": 85, "identified": true, "properties": [{"name": "Bow", "values": [], "displayMode": 0}, {"name": "Quality", "values": [["+20%", 1]], "displayMode": 0, "type": 6}, {"name": "Physical Damage", "values": [["48-147", 1]], "displayMode": 0, "type": 9}, {"name": "Elemental Damage", "values": [["108-187", 4]], "displayMode": 0, "type": 10}, {"name": "Critical Strike Chance", "values": [["5.00%", 0]], "displayMode": 0, "type": 12}, {"name": "Attacks per Second", "values": [["1.50", 0]], "displayMode": 0, "type": 13}], "requirements": [{"name": "Level", "values": [["56", 0]], "displayMode": 0, "type": 62}, {"name": "Dex", "values": [["116", 0]], "displayMode": 1, "type": 64}], "explicitMods": ["+40 to Dexterity", "101% increased Physical Damage", "Adds 108 to 187 Fire Damage", "Grants 23 Life per Enemy Hit", "24% increased Stun Duration on Enemies"], "frameType": 2, "x": 0, "y": 0, "inventoryId": "Weapon2", "socketedItems": []}]